src/domain/entities/__init__.py
src/domain/entities/cliente.py
src/domain/entities/conta.py
src/domain/entities/conta_corrente.py
src/domain/entities/deposito.py
src/domain/entities/historico.py
src/domain/entities/pessoa_fisica.py
src/domain/entities/saque.py
src/domain/entities/transacao.py
src/domain/repository/RepositoryBankManegement.py
src/domain/repository/__init__.py
src/utils/__init__.py
src/utils/menu.py
sistema_bancario_poo-0.0.5.dist-info/METADATA
sistema_bancario_poo-0.0.5.dist-info/WHEEL
sistema_bancario_poo-0.0.5.dist-info/top_level.txt
sistema_bancario_poo-0.0.5.dist-info/RECORD
