Metadata-Version: 2.1
Name: sistema-bancario-poo
Version: 0.0.5
Summary: Processamento e comparação de similaridade entre imagens.
Home-page: https://github.com/DanielyFX/sistema-bancario-poo
Author: Daniely de Faria Xavier
Author-email: danixavier815@gmail.com
Requires-Python: >=3.8
